Metadata-Version: 2.1
Name: django-ui-widgets
Version: 1.51b0
Summary: Library of django ui widgets
Home-page: https://github.com/Sanshain/django-ui-widgets
Author: Alexander
Author-email: digital-mag@ya.ru
License: AGPL
Keywords: django,forms,widgets,fields,django-ui
Platform: UNKNOWN
Classifier: Development Status :: 4 - Beta
Classifier: Environment :: Web Environment
Classifier: Framework :: Django
Classifier: Framework :: Django :: 3.0
Classifier: Framework :: Django :: 3.1
Classifier: Intended Audience :: Developers
Classifier: License :: OSI Approved :: MIT License
Classifier: Natural Language :: English
Classifier: Operating System :: OS Independent
Classifier: Programming Language :: Python :: 3
Classifier: Programming Language :: Python :: 3.5
Classifier: Programming Language :: Python :: 3.6
Classifier: Programming Language :: Python :: 3.7
Classifier: Programming Language :: Python :: 3.8
Classifier: Topic :: Software Development :: Build Tools
